pypug/__init__.py
pypug-0.0.5.dist-info/METADATA
pypug-0.0.5.dist-info/RECORD
pypug-0.0.5.dist-info/WHEEL
pypug-0.0.5.dist-info/entry_points.txt
pypug-0.0.5.dist-info/top_level.txt
